MANIFEST.in
README.md
setup.py
galileo_scope_components/Button.py
galileo_scope_components/CustomStylesheet.py
galileo_scope_components/HydraJobSelectionBox.py
galileo_scope_components/Layout.py
galileo_scope_components/Stylesheet.py
galileo_scope_components/TextInput.py
galileo_scope_components/Typography.py
galileo_scope_components/__init__.py
galileo_scope_components/_imports_.py
galileo_scope_components/galileo_scope_components.dev.js
galileo_scope_components/galileo_scope_components.min.js
galileo_scope_components/metadata.json
galileo_scope_components/package.json
galileo_scope_components.egg-info/PKG-INFO
galileo_scope_components.egg-info/SOURCES.txt
galileo_scope_components.egg-info/dependency_links.txt
galileo_scope_components.egg-info/top_level.txt
galileo_scope_components/fonts/Inter-UI-Bold.woff
galileo_scope_components/fonts/Inter-UI-Bold.woff2
galileo_scope_components/fonts/Inter-UI-BoldItalic.woff
galileo_scope_components/fonts/Inter-UI-BoldItalic.woff2
galileo_scope_components/fonts/Inter-UI-Italic.woff
galileo_scope_components/fonts/Inter-UI-Italic.woff2
galileo_scope_components/fonts/Inter-UI-Medium.woff
galileo_scope_components/fonts/Inter-UI-Medium.woff2
galileo_scope_components/fonts/Inter-UI-MediumItalic.woff
galileo_scope_components/fonts/Inter-UI-MediumItalic.woff2
galileo_scope_components/fonts/Inter-UI-Regular.woff
galileo_scope_components/fonts/Inter-UI-Regular.woff2
galileo_scope_components/fonts/roboto-latin-100.woff
galileo_scope_components/fonts/roboto-latin-100.woff2
galileo_scope_components/fonts/roboto-latin-100italic.woff
galileo_scope_components/fonts/roboto-latin-100italic.woff2
galileo_scope_components/fonts/roboto-latin-300.woff
galileo_scope_components/fonts/roboto-latin-300.woff2
galileo_scope_components/fonts/roboto-latin-300italic.woff
galileo_scope_components/fonts/roboto-latin-300italic.woff2
galileo_scope_components/fonts/roboto-latin-400.woff
galileo_scope_components/fonts/roboto-latin-400.woff2
galileo_scope_components/fonts/roboto-latin-400italic.woff
galileo_scope_components/fonts/roboto-latin-400italic.woff2
galileo_scope_components/fonts/roboto-latin-500.woff
