Metadata-Version: 1.0
Name: galileo-scope-components
Version: 0.1.2
Summary: Dash components for Galileo Scopes
Home-page: UNKNOWN
Author: Nick Radford nick.radford@getcruise.com
Author-email: UNKNOWN
License: UNLICENSED
Platform: UNKNOWN
